lim/__init__.py
lim/cli.py
lim/core.py
lim/validator.py
lim_mm_cli-0.1.7.dist-info/licenses/LICENSE
mm/__init__.py
mm/cli.py
mm/core.py
mm/validator.py
mm/template/README.md
mm/template/__init__.py
mm/template/meta.json
mm/template/requirements.txt
mm/template/data/.gitkeep
mm/template/mms/app/.gitkeep
mm/template/mms/tests/.gitkeep
mm/template/models/default/.gitkeep
mm/template/run/start.py
mm/template/run/docker/.gitkeep
lim_mm_cli-0.1.7.dist-info/METADATA
lim_mm_cli-0.1.7.dist-info/WHEEL
lim_mm_cli-0.1.7.dist-info/entry_points.txt
lim_mm_cli-0.1.7.dist-info/top_level.txt
lim_mm_cli-0.1.7.dist-info/RECORD
