Metadata-Version: 2.4
Name: lim-mm-cli
Version: 0.1.7
Summary: CLI tool for LIM-compatible micro model project scaffolding
Author-email: Solution Eden <solutionedencom@gmail.com>
Requires-Python: >=3.7
License-File: LICENSE
Requires-Dist: typer[all]
Requires-Dist: jsonschema
Requires-Dist: requests
Dynamic: license-file
